mozphab/__init__.py
mozphab/__main__.py
mozphab/args.py
mozphab/bmo.py
mozphab/commits.py
mozphab/conduit.py
mozphab/config.py
mozphab/detect_repository.py
mozphab/diff.py
mozphab/environment.py
mozphab/exceptions.py
mozphab/git.py
mozphab/gitcommand.py
mozphab/helpers.py
mozphab/jujutsu.py
mozphab/logger.py
mozphab/mercurial.py
mozphab/metrics.yaml
mozphab/mozphab.py
mozphab/patch.py
mozphab/pings.yaml
mozphab/repository.py
mozphab/sentry.py
mozphab/simplecache.py
mozphab/spinner.py
mozphab/subprocess_wrapper.py
mozphab/telemetry.py
mozphab/updater.py
mozphab/user.py
mozphab/commands/__init__.py
mozphab/commands/abandon.py
mozphab/commands/doctor.py
mozphab/commands/install_certificate.py
mozphab/commands/patch.py
mozphab/commands/reorganise.py
mozphab/commands/self_update.py
mozphab/commands/submit.py
mozphab/commands/uplift.py
mozphab/commands/version.py
mozphab-2.8.2.dist-info/licenses/LICENSE
mozphab-2.8.2.dist-info/METADATA
mozphab-2.8.2.dist-info/WHEEL
mozphab-2.8.2.dist-info/entry_points.txt
mozphab-2.8.2.dist-info/top_level.txt
mozphab-2.8.2.dist-info/RECORD
