Metadata-Version: 2.4
Name: MozPhab
Version: 2.8.2
Summary: Phabricator review submission/management tool.
Author-email: Mozilla <conduit-team@mozilla.com>
License-Expression: MPL-2.0
Project-URL: Repository, https://github.com/mozilla-conduit/review
Project-URL: Bug Tracker, https://bugzilla.mozilla.org
Classifier: Development Status :: 5 - Production/Stable
Classifier: Environment :: Console
Classifier: Intended Audience :: Developers
Classifier: Operating System :: OS Independent
Classifier: Programming Language :: Python :: 3 :: Only
Classifier: Topic :: Software Development :: Version Control :: Git
Classifier: Topic :: Software Development :: Version Control :: Mercurial
Requires-Python: >=3.9
License-File: LICENSE
Requires-Dist: distro
Requires-Dist: glean-sdk==65.*
Requires-Dist: packaging
Requires-Dist: python-hglib>=2.6.2
Requires-Dist: sentry-sdk>=0.14.3
Requires-Dist: setuptools
Requires-Dist: colorama>=0.4.6
Dynamic: license-file
